deepdrive_ci/ContainerSpawner.py
deepdrive_ci/JobRunner.py
deepdrive_ci/PlatformDefaults.py
deepdrive_ci/TargetPlatform.py
deepdrive_ci/__init__.py
deepdrive_ci-0.0.5.dist-info/LICENSE
deepdrive_ci-0.0.5.dist-info/METADATA
deepdrive_ci-0.0.5.dist-info/WHEEL
deepdrive_ci-0.0.5.dist-info/top_level.txt
deepdrive_ci-0.0.5.dist-info/zip-safe
deepdrive_ci-0.0.5.dist-info/RECORD
